acfx/ACFX.py
acfx/AcfxCustom.py
acfx/AcfxEBM.py
acfx/AcfxLinear.py
acfx/RandomSearchCounterOptimizer.py
acfx/__init__.py
acfx/abstract/ModelBasedCounterOptimizer.py
acfx/abstract/OptimizerType.py
acfx/abstract/__init__.py
acfx/evaluation/EBMCounterOptimizer.py
acfx/evaluation/LogisticRegressionCounterOptimizer.py
acfx/evaluation/__init__.py
acfx/evaluation/bayesian_model.py
acfx/evaluation/ccfs.py
acfx/evaluation/loss.py
acfx/evaluation/multi_dataset_evaluation.py
acfx/evaluation/utils.py
acfx-0.3.5.dist-info/licenses/LICENSE
acfx-0.3.5.dist-info/METADATA
acfx-0.3.5.dist-info/WHEEL
acfx-0.3.5.dist-info/top_level.txt
acfx-0.3.5.dist-info/RECORD
